ishneholterlib/__init__.py
ishneholterlib-2020.5.29.dist-info/LICENSE
ishneholterlib-2020.5.29.dist-info/METADATA
ishneholterlib-2020.5.29.dist-info/WHEEL
ishneholterlib-2020.5.29.dist-info/top_level.txt
ishneholterlib-2020.5.29.dist-info/RECORD
