Metadata-Version: 2.1
Name: ishneholterlib
Version: 2020.5.29
Summary: A library to work with ISHNE-formatted Holter ECG files
Home-page: https://bitbucket.org/atpage/ishneholterlib
Author: Alex Page
Author-email: alex.page@rochester.edu
License: MIT
Keywords: ISHNE Holter ECG EKG
Platform: UNKNOWN
Requires-Dist: crccheck
Requires-Dist: numpy
